Workbook

Sheet Executive Summary
A1: Multi-Family Investment Pro Forma
A2: Property Name: | B2: Weinland Park Summit Portfolio
A3: Date: | B3: 10/20/2025
A5: PROPERTY OVERVIEW
A6: Total Units: | B6: ='Model Inputs'!B5 -> 32
A7: Acquisition Price: | B7: ='Model Inputs'!B4 -> 3200000
A8: Price per Unit: | B8: =B7/B6 -> 100000
A9: Total Project Cost: | B9: ='Model Inputs'!B6 -> 3768000
A10: Equity Required: | B10: ='Capital Stack'!B6+'Capital Stack'!B7 -> 810400
A11: Debt Amount: | B11: ='Model Inputs'!B7 -> 2637600
A12: LTC Ratio: | B12: =IF(B9>0,B11/B9,0) -> 0.7
A14: KEY METRICS
A15: Cash-on-Cash Return: | B15: {=AVERAGE('Cash Flow'!F4:INDEX('Cash Flow'!F:F,3+'Model Inputs'!B18))} -> 0.052108066
A16: Levered IRR: | B16: {=IRR('Cash Flow'!H3:INDEX('Cash Flow'!H:H,3+'Model Inputs'!B18))} -> 0.22626499
A17: Equity Multiple: | B17: {=IF(ABS('Cash Flow'!H3)>0, SUM('Cash Flow'!H4:INDEX('Cash Flow'!H:H,3+'Model Inputs'!B18))/ABS('Cash Flow'!H3), 0)} -> 2.1765703
A18: DSCR (Year 1): | B18: =IF('Cash Flow'!C4>0, 'Cash Flow'!B4/'Cash Flow'!C4, 0) -> 1.265785
A19: Avg DSCR (Hold): | B19: {=ROUND(AVERAGE(IFERROR('Cash Flow'!B4:INDEX('Cash Flow'!B:B,3+'Model Inputs'!B18)/'Cash Flow'!C4:INDEX('Cash Flow'!C:C,3+'Model Inputs'!B18),0)), 2) & "x"} -> 1.28x
A21: LENDER UNDERWRITING
A22: DSCR Day-1 (Ramped): | B22: =IF('Cash Flow'!C4>0, 'Cash Flow'!B4/'Cash Flow'!C4, 0) -> 1.265785
A23: DSCR Stabilized: | B23: {=IF(INDEX('Model Inputs'!B41:B45,2)>0, IF('Model Inputs'!B48>0,'Model Inputs'!B48, 'Model Inputs'!B16*(1+'Model Inputs'!B17)*(1-('Model Inputs'!B21-('Model Inputs'!B21-'Model Inputs'!B22)*MIN(1,'Model Inputs'!B23)/MAX(1,'Model Inputs'!B23)))) / INDEX('Model Inputs'!B41:B45,2), 0)} -> 1.3712157
A24: Debt Yield Day-1: | B24: =IF('Model Inputs'!B7>0, 'Cash Flow'!B4/'Model Inputs'!B7, 0) -> 0.091769412
A25: Debt Yield Stabilized: | B25: =IF('Model Inputs'!B7>0, IF('Model Inputs'!B48>0,'Model Inputs'!B48, 'Model Inputs'!B16*(1+'Model Inputs'!B17)*(1-('Model Inputs'!B21-('Model Inputs'!B21-'Model Inputs'!B22)*MIN(1,'Model Inputs'!B23)/MAX(1,'Model Inputs'!B23)))) / 'Model Inputs'!B7, 0) -> 0.10815666
A26: Suggested IO Months: | B26: =IF('Model Inputs'!B7>0, IF(('Cash Flow'!B4/12/1.2)>=ABS(PMT('Model Inputs'!B8/12,'Model Inputs'!B10*12,'Model Inputs'!B7)), 0, MIN(24, ROUNDUP(12*(ABS(PMT('Model Inputs'!B8/12,'Model Inputs'!B10*12,'Model Inputs'!B7)) - ('Cash Flow'!B4/12/1.2)) / (ABS(PMT('Model Inputs'!B8/12,'Model Inputs'!B10*12,'Model Inputs'!B7)) - ('Model Inputs'!B7*'Model Inputs'!B8/12)), 0))), 0) -> 7
A27: Interest Reserve (est.): | B27: =MAX(0, B26 * MAX(0, ('Model Inputs'!B7*'Model Inputs'!B8/12) - ('Cash Flow'!B4/12/1.2))) -> 0

Sheet Assumptions
A1: KEY ASSUMPTIONS & CALCULATIONS
A3: REVENUE ASSUMPTIONS
A4: Average Monthly Rent (Per Unit): | B4: 1140
A5: Occupancy Rate: | B5: 0.96
A6: Units: | B6: 32
A7: Annual Rent Growth: | B7: 0.032
A8: Other Income (Monthly): | B8: 3200
A9: Delinquency Y1: | B9: 0.02
A10: Delinquency Y2+ (Stabilized): | B10: 0.02
A11: Delinquency Ramp Years: | B11: 1
A13: OPERATING EXPENSES
A14: Property Taxes: | B14: 51325
A15: Insurance: | B15: 15000
A16: Utilities: | B16: 25635.59
A17: Repairs & Maintenance: | B17: 45000
A18: Management Fee: | B18: =B28*'Model Inputs'!B24 -> 18009.784
A19: Other Expenses: | B19: 10000
A21: RESERVES (Per Unit)
A22: Annual CapEx ($/Unit): | B22: 250
A23: Leasing Costs ($/Unit): | B23: 400
A24: TI Allowance ($/Unit): | B24: 0
A26: CALCULATED RESULTS
A27: Gross Rental Income: | B27: =B4*B6*12 -> 437760
A28: Effective Gross Income: | B28: =B27*B5*(1-B9)+(B8*12) -> 450244.61
A29: Total Operating Expenses: | B29: =B14+B15+B16+B17+B18+B19 -> 164970.37
A30: Net Operating Income: | B30: =(B28)*((12-IFERROR('Model Inputs'!B46,0)+IFERROR('Model Inputs'!B46,0)*(1-IFERROR('Model Inputs'!B47,0)))/12)-B29 -> 240249.77
A31: Expense Ratio: | B31: =B29/B28 -> 0.36640167

Sheet Capital Stack
A1: CAPITAL STACK
A3: Source | B3: Amount | C3: % of Total | D3: Cost/Return
A4: Senior Debt | B4: ='Model Inputs'!B7 -> 2637600 | C4: =IF('Model Inputs'!B6>0,B4/'Model Inputs'!B6,0) -> 0.7 | D4: ='Model Inputs'!B8 -> 0.0725
A5: Seller Note | B5: ='Model Inputs'!B56 -> 320000 | C5: =IF('Model Inputs'!B6>0,B5/'Model Inputs'!B6,0) -> 0.08492569 | D5: ='Model Inputs'!B52 -> 0.05
A6: LP Equity | B6: =IF('Model Inputs'!B6>0,('Model Inputs'!B6-'Model Inputs'!B7-'Model Inputs'!B56)*'Model Inputs'!B13,0) -> 769880 | C6: =IF('Model Inputs'!B6>0,B6/'Model Inputs'!B6,0) -> 0.20432059 | D6: ='Model Inputs'!B14 -> 0.07
A7: GP Equity | B7: =IF('Model Inputs'!B6>0,('Model Inputs'!B6-'Model Inputs'!B7-'Model Inputs'!B56)*'Model Inputs'!B12,0) -> 40520 | C7: =IF('Model Inputs'!B6>0,B7/'Model Inputs'!B6,0) -> 0.010753716 | D7: Residual
A8: Total | B8: ='Model Inputs'!B6 -> 3768000 | C8: 1

Sheet Cash Flow
A1: 5-YEAR CASH FLOW PROJECTION
H2: CF
A3: Year | B3: NOI | C3: Debt Service | D3: Reserves | E3: Before-Tax CF | F3: Cash-on-Cash | H3: =-1*('Capital Stack'!B6+'Capital Stack'!B7) -> -810400
A4: Year 1 | B4: ='Model Inputs'!B16 -> 242051 | C4: ='Model Inputs'!B41 -> 191226 | D4: =(Assumptions!B22+Assumptions!B23+Assumptions!B24)*'Model Inputs'!B5 -> 20800 | E4: =B4-C4-D4 -> 30025 | F4: =IF(('Capital Stack'!B6+'Capital Stack'!B7)>0, E4/('Capital Stack'!B6+'Capital Stack'!B7), 0) -> 0.037049605 | H4: =E4 + IF(1='Model Inputs'!B29, Refinance!B6, 0) -> 30025
A5: Year 2 | B5: =IF('Model Inputs'!B48>0,'Model Inputs'!B48,('Model Inputs'!B16*(1+'Model Inputs'!B17)*(1-('Model Inputs'!B21-('Model Inputs'!B21-'Model Inputs'!B22)*MIN(1,'Model Inputs'!B23)/MAX(1,'Model Inputs'!B23))))) -> 285274 | C5: ='Model Inputs'!B42 -> 208044.59 | D5: =(Assumptions!B22+Assumptions!B23+Assumptions!B24)*'Model Inputs'!B5 -> 20800 | E5: =B5-C5-D5 -> 56429.41 | F5: =IF(('Capital Stack'!B6+'Capital Stack'!B7)>0, E5/('Capital Stack'!B6+'Capital Stack'!B7), 0) -> 0.069631552 | H5: =E5 + IF(2='Model Inputs'!B29, Refinance!B6, 0) -> 497427.41
A6: Year 3 | B6: =(IF('Model Inputs'!B48>0,'Model Inputs'!B48,('Model Inputs'!B16*(1+'Model Inputs'!B17)*(1-('Model Inputs'!B21-('Model Inputs'!B21-'Model Inputs'!B22)*MIN(1,'Model Inputs'!B23)/MAX(1,'Model Inputs'!B23))))))*POWER(1+'Model Inputs'!B17,1) -> 294402.77 | C6: ='Model Inputs'!B43 -> 241561.66 | D6: =(Assumptions!B22+Assumptions!B23+Assumptions!B24)*'Model Inputs'!B5 -> 20800 | E6: =B6-C6-D6 -> 32041.113 | F6: =IF(('Capital Stack'!B6+'Capital Stack'!B7)>0, E6/('Capital Stack'!B6+'Capital Stack'!B7), 0) -> 0.039537405 | H6: =E6 + IF(3='Model Inputs'!B29, Refinance!B6, 0) -> 32041.113
A7: Year 4 | B7: =(IF('Model Inputs'!B48>0,'Model Inputs'!B48,('Model Inputs'!B16*(1+'Model Inputs'!B17)*(1-('Model Inputs'!B21-('Model Inputs'!B21-'Model Inputs'!B22)*MIN(1,'Model Inputs'!B23)/MAX(1,'Model Inputs'!B23))))))*POWER(1+'Model Inputs'!B17,2) -> 303823.66 | C7: ='Model Inputs'!B44 -> 241561.66 | D7: =(Assumptions!B22+Assumptions!B23+Assumptions!B24)*'Model Inputs'!B5 -> 20800 | E7: =B7-C7-D7 -> 41462.001 | F7: =IF(('Capital Stack'!B6+'Capital Stack'!B7)>0, E7/('Capital Stack'!B6+'Capital Stack'!B7), 0) -> 0.051162391 | H7: =E7 + IF(4='Model Inputs'!B29, Refinance!B6, 0) -> 41462.001
A8: Year 5 | B8: =(IF('Model Inputs'!B48>0,'Model Inputs'!B48,('Model Inputs'!B16*(1+'Model Inputs'!B17)*(1-('Model Inputs'!B21-('Model Inputs'!B21-'Model Inputs'!B22)*MIN(1,'Model Inputs'!B23)/MAX(1,'Model Inputs'!B23))))))*POWER(1+'Model Inputs'!B17,3) -> 313546.01 | C8: ='Model Inputs'!B45 -> 241561.66 | D8: =(Assumptions!B22+Assumptions!B23+Assumptions!B24)*'Model Inputs'!B5 -> 20800 | E8: =B8-C8-D8 -> 51184.358 | F8: =IF(('Capital Stack'!B6+'Capital Stack'!B7)>0, E8/('Capital Stack'!B6+'Capital Stack'!B7), 0) -> 0.063159376 | H8: =E8 + ((('Model Inputs'!B16*POWER(1+'Model Inputs'!B17,'Model Inputs'!B18))/'Model Inputs'!B19)*(1-'Model Inputs'!B20)) - (IF(AND('Model Inputs'!B29>0,'Model Inputs'!B18>'Model Inputs'!B29,'Model Inputs'!B38>0),IF(MIN(MAX(0,('Model Inputs'!B18-'Model Inputs'!B29)*12),'Model Inputs'!B31*12)>0,IF('Model Inputs'!B30>0,'Model Inputs'!B38*POWER(1+'Model Inputs'!B30/12,MIN(MAX(0,('Model Inputs'!B18-'Model Inputs'!B29)*12),'Model Inputs'!B31*12))-ABS(PMT('Model Inputs'!B30/12,'Model Inputs'!B31*12,'Model Inputs'!B38))*((POWER(1+'Model Inputs'!B30/12,MIN(MAX(0,('Model Inputs'!B18-'Model Inputs'!B29)*12),'Model Inputs'!B31*12))-1)/('Model Inputs'!B30/12)),MAX(0,'Model Inputs'!B38-ABS(PMT('Model Inputs'!B30/12,'Model Inputs'!B31*12,'Model Inputs'!B38))*MIN(MAX(0,('Model Inputs'!B18-'Model Inputs'!B29)*12),'Model Inputs'!B31*12))),'Model Inputs'!B38),IF(MAX(0,MIN('Model Inputs'!B18*12,'Model Inputs'!B9*12)-'Model Inputs'!B25)>0,IF('Model Inputs'!B8>0,'Model Inputs'!B7*POWER(1+'Model Inputs'!B8/12,MAX(0,MIN('Model Inputs'!B18*12,'Model Inputs'!B9*12)-'Model Inputs'!B25))-ABS(PMT('Model Inputs'!B8/12,'Model Inputs'!B10*12,'Model Inputs'!B7))*((POWER(1+'Model Inputs'!B8/12,MAX(0,MIN('Model Inputs'!B18*12,'Model Inputs'!B9*12)-'Model Inputs'!B25))-1)/('Model Inputs'!B8/12)),MAX(0,'Model Inputs'!B7-ABS(PMT('Model Inputs'!B8/12,'Model Inputs'!B10*12,'Model Inputs'!B7))*MAX(0,MIN('Model Inputs'!B18*12,'Model Inputs'!B9*12)-'Model Inputs'!B25))),'Model Inputs'!B7))) + IF(5='Model Inputs'!B29, Refinance!B6, 0) -> 1162937

Sheet Refinance
A1: REFINANCE SUMMARY
A3: Sizing Method | B3: ltv
A4: Refi Year | B4: 2
A5: Perm Loan Amount | B5: 3449464
A6: Net Refi Proceeds | B6: 440998
A7: Value at Refi | B7: 4450922
A8: Bridge Payoff | B8: 2637600
A9: Seller Note Payoff | B9: 336372
A10: Perm Points/Fees | B10: 34495

Sheet Notes
A1: NOTES
A3: Bridge LTV | B3: 0.7
A4: Bridge LTC | B4: 0.7
A5: Bridge IO Months | B5: 24
A6: Sizing Method | B6: ltv

Sheet Model Inputs
A1: ALL MODEL INPUTS FOR PRO FORMA
A3: Input Field | B3: Value
A4: Purchase Price | B4: 3200000
A5: Units | B5: 32
A6: Total Project Cost | B6: 3768000
A7: Loan Amount | B7: 2637600
A8: Interest Rate | B8: 0.0725
A9: Loan Term | B9: 2
A10: Amortization | B10: 30
A11: LTV | B11: 0.7
A12: GP Investment % | B12: 0.05
A13: LP Investment % | B13: 0.95
A14: Preferred Return | B14: 0.07
A15: GP Promote | B15: 0.3
... A36: Perm Points | B36: 0.01
A37: Sizing Method | B37: ltv
A38: Perm Loan Sized (PV) | B38: =IF('Model Inputs'!B37="ltv", 'Model Inputs'!B39, IF('Model Inputs'!B37="dscr", 'Model Inputs'!B40, MIN('Model Inputs'!B39,'Model Inputs'!B40))) -> 3449464.4
A39: Perm Loan LTV | B39: =(('Model Inputs'!B16*POWER(1+'Model Inputs'!B17,'Model Inputs'!B29-1)*(1-IF('Model Inputs'!B29=1,'Model Inputs'!B21, 'Model Inputs'!B21-('Model Inputs'!B21-'Model Inputs'!B22)*MIN('Model Inputs'!B29-1,'Model Inputs'!B23)/MAX(1,'Model Inputs'!B23))))/'Model Inputs'!B35)*'Model Inputs'!B33 -> 3449464.4
A40: Perm Loan DSCR | B40: =((('Model Inputs'!B16*POWER(1+'Model Inputs'!B17,'Model Inputs'!B29-1)*(1-IF('Model Inputs'!B29=1,'Model Inputs'!B21, 'Model Inputs'!B21-('Model Inputs'!B21-'Model Inputs'!B22)*MIN('Model Inputs'!B29-1,'Model Inputs'!B23)/MAX(1,'Model Inputs'!B23))))/'Model Inputs'!B34)/12)*((1-POWER(1+'Model Inputs'!B30/12,-'Model Inputs'!B31*12))/('Model Inputs'!B30/12)) -> 2796574
A41: Debt Service Year 1 | B41: =IF(1<='Model Inputs'!B29, MAX(0,MIN(1*12,'Model Inputs'!B25)-0*12)*('Model Inputs'!B7*'Model Inputs'!B8/12) + (12-MAX(0,MIN(1*12,'Model Inputs'!B25)-0*12))*ABS(PMT('Model Inputs'!B8/12,'Model Inputs'!B10*12,'Model Inputs'!B7)) + IF('Model Inputs'!B49=1, MAX(0, MIN(1*12, IF('Model Inputs'!B29>0, 'Model Inputs'!B29*12, 99999), 'Model Inputs'!B53+'Model Inputs'!B54) - MAX(0*12, 'Model Inputs'!B53))*'Model Inputs'!B58, 0), ABS(PMT('Model Inputs'!B30/12,'Model Inputs'!B31*12,'Model Inputs'!B38))*12) -> 191226
A42: Debt Service Year 2 | B42: =IF(2<='Model Inputs'!B29, MAX(0,MIN(2*12,'Model Inputs'!B25)-1*12)*('Model Inputs'!B7*'Model Inputs'!B8/12) + (12-MAX(0,MIN(2*12,'Model Inputs'!B25)-1*12))*ABS(PMT('Model Inputs'!B8/12,'Model Inputs'!B10*12,'Model Inputs'!B7)) + IF('Model Inputs'!B49=1, MAX(0, MIN(2*12, IF('Model Inputs'!B29>0, 'Model Inputs'!B29*12, 99999), 'Model Inputs'!B53+'Model Inputs'!B54) - MAX(1*12, 'Model Inputs'!B53))*'Model Inputs'!B58, 0), ABS(PMT('Model Inputs'!B30/12,'Model Inputs'!B31*12,'Model Inputs'!B38))*12) -> 208044.59
A43: Debt Service Year 3 | B43: =IF(3<='Model Inputs'!B29, MAX(0,MIN(3*12,'Model Inputs'!B25)-2*12)*('Model Inputs'!B7*'Model Inputs'!B8/12) + (12-MAX(0,MIN(3*12,'Model Inputs'!B25)-2*12))*ABS(PMT('Model Inputs'!B8/12,'Model Inputs'!B10*12,'Model Inputs'!B7)) + IF('Model Inputs'!B49=1, MAX(0, MIN(3*12, IF('Model Inputs'!B29>0, 'Model Inputs'!B29*12, 99999), 'Model Inputs'!B53+'Model Inputs'!B54) - MAX(2*12, 'Model Inputs'!B53))*'Model Inputs'!B58, 0), ABS(PMT('Model Inputs'!B30/12,'Model Inputs'!B31*12,'Model Inputs'!B38))*12) -> 241561.66
A44: Debt Service Year 4 | B44: =IF(4<='Model Inputs'!B29, MAX(0,MIN(4*12,'Model Inputs'!B25)-3*12)*('Model Inputs'!B7*'Model Inputs'!B8/12) + (12-MAX(0,MIN(4*12,'Model Inputs'!B25)-3*12))*ABS(PMT('Model Inputs'!B8/12,'Model Inputs'!B10*12,'Model Inputs'!B7)) + IF('Model Inputs'!B49=1, MAX(0, MIN(4*12, IF('Model Inputs'!B29>0, 'Model Inputs'!B29*12, 99999), 'Model Inputs'!B53+'Model Inputs'!B54) - MAX(3*12, 'Model Inputs'!B53))*'Model Inputs'!B58, 0), ABS(PMT('Model Inputs'!B30/12,'Model Inputs'!B31*12,'Model Inputs'!B38))*12) -> 241561.66
A45: Debt Service Year 5 | B45: =IF(5<='Model Inputs'!B29, MAX(0,MIN(5*12,'Model Inputs'!B25)-4*12)*('Model Inputs'!B7*'Model Inputs'!B8/12) + (12-MAX(0,MIN(5*12,'Model Inputs'!B25)-4*12))*ABS(PMT('Model Inputs'!B8/12,'Model Inputs'!B10*12,'Model Inputs'!B7)) + IF('Model Inputs'!B49=1, MAX(0, MIN(5*12, IF('Model Inputs'!B29>0, 'Model Inputs'!B29*12, 99999), 'Model Inputs'!B53+'Model Inputs'!B54) - MAX(4*12, 'Model Inputs'!B53))*'Model Inputs'!B58, 0), ABS(PMT('Model Inputs'!B30/12,'Model Inputs'!B31*12,'Model Inputs'!B38))*12) -> 241561.66
A46: Y1 Ramp Months | B46: 8
A47: Y1 Ramp Discount | B47: 0.15
A48: Year 2 NOI (Stabilized) | B48: 285274
A49: Seller Note Enabled | B49: 1
A50: Seller Note % of Purchase | B50: 0.1
A51: Seller Note Fixed Amount | B51: 0
A52: Seller Interest Rate | B52: 0.05
A53: Seller Accrual Months | B53: 12
A54: Seller Payment Months | B54: 12
A55: Seller Compounding (1=yes) | B55: 1
A56: Seller Principal | B56: =IF(B49=1,IF(B51>0,B51,B4*B50),0) -> 320000
A57: Seller Balance After Accrual | B57: =IF(B49=1,IF(B55=1,B56*POWER(1+B52/12,B53),B56+B56*B52/12*B53),0) -> 336371.81
A58: Seller Monthly IO | B58: =B57*B52/12 -> 1401.5492
A59: Seller Payoff at Refi | B59: =IF(AND(B49=1,B29>0),IF(B29*12<=B53,IF(B55=1,B56*POWER(1+B52/12,B29*12),B56+B56*B52/12*(B29*12)),B57),0) -> 336371.81
